alpharaw/__init__.py
alpharaw/cli.py
alpharaw/ms_data_base.py
alpharaw/mzml.py
alpharaw/sciex.py
alpharaw/thermo.py
alpharaw/dia/normal_dia.py
alpharaw/ext/__init__.py
alpharaw/ext/sciex/Clearcore2.Compression.dll
alpharaw/ext/sciex/Clearcore2.Data.Acquisition.Client.dll
alpharaw/ext/sciex/Clearcore2.Data.Acquisition.Contracts.dll
alpharaw/ext/sciex/Clearcore2.Data.AnalystDataProvider.dll
alpharaw/ext/sciex/Clearcore2.Data.Client.dll
alpharaw/ext/sciex/Clearcore2.Data.Common.dll
alpharaw/ext/sciex/Clearcore2.Data.CommonInterfaces.dll
alpharaw/ext/sciex/Clearcore2.Data.Contracts.dll
alpharaw/ext/sciex/Clearcore2.Data.Core.dll
alpharaw/ext/sciex/Clearcore2.Data.Wiff2.dll
alpharaw/ext/sciex/Clearcore2.Data.WiffReader.dll
alpharaw/ext/sciex/Clearcore2.Data.dll
alpharaw/ext/sciex/Clearcore2.DataService.dll
alpharaw/ext/sciex/Clearcore2.Devices.Types.dll
alpharaw/ext/sciex/Clearcore2.Domain.Acquisition.Methods.MassSpec.dll
alpharaw/ext/sciex/Clearcore2.Domain.Acquisition.dll
alpharaw/ext/sciex/Clearcore2.Infrastructure.dll
alpharaw/ext/sciex/Clearcore2.InternalRawXYProcessing.dll
alpharaw/ext/sciex/Clearcore2.Muni.dll
alpharaw/ext/sciex/Clearcore2.RawXYProcessing.dll
alpharaw/ext/sciex/Clearcore2.StructuredStorage.dll
alpharaw/ext/sciex/Clearcore2.UserLog.Types.dll
alpharaw/ext/sciex/Clearcore2.Utility.dll
alpharaw/ext/sciex/Clearcore2.XmlHelpers.dll
alpharaw/ext/sciex/Sciex.Clearcore.FMan.dll
alpharaw/ext/sciex/Sciex.Data.Processing.dll
alpharaw/ext/sciex/Sciex.Data.SimpleTypes.dll
alpharaw/ext/sciex/Sciex.Data.XYData.dll
alpharaw/ext/sciex/Sciex.FMan.dll
alpharaw/ext/sciex/Sciex.Wiff.dll
alpharaw/ext/sciex/SciexToolKit.dll
alpharaw/ext/sciex/WiffOps4Python.dll
alpharaw/ext/sciex/protobuf-net.dll
alpharaw/ext/thermo_fisher/THERMO_LICENSE.txt
alpharaw/ext/thermo_fisher/ThermoFisher.CommonCore.Data.dll
alpharaw/ext/thermo_fisher/ThermoFisher.CommonCore.RawFileReader.dll
alpharaw/feature/__init__.py
alpharaw/feature/centroids.py
alpharaw/feature/chem.py
alpharaw-0.4.8.dist-info/licenses/LICENSE.txt
alpharaw-0.4.8.dist-info/METADATA
alpharaw-0.4.8.dist-info/WHEEL
alpharaw-0.4.8.dist-info/entry_points.txt
alpharaw-0.4.8.dist-info/top_level.txt
alpharaw-0.4.8.dist-info/RECORD
