Metadata-Version: 2.4
Name: alpharaw
Version: 0.4.8
Summary: An open-source Python package to unify raw MS data access and storage.
Author-email: Mann Labs <jalew188@gmail.com>
License:                                  Apache License
Project-URL: Repository, https://github.com/MannLabs/alpharaw
Project-URL: Issues, https://github.com/MannLabs/alpharaw/issues
Project-URL: Mann Labs Homepage, https://www.biochem.mpg.de/mann
Keywords: mass spectrometry,proteomics,bioinformatics,mass spectrometry,raw data,data access,data storage,AlphaPept,AlphaPept ecosystem,AlphaX ecosystem
Classifier: Development Status :: 3 - Alpha
Classifier: Intended Audience :: Science/Research
Classifier: License :: OSI Approved :: Apache Software License
Classifier: Operating System :: OS Independent
Classifier: Programming Language :: Python :: 3
Classifier: Topic :: Scientific/Engineering :: Bio-Informatics
Requires-Python: >=3.8
License-File: LICENSE.txt
Requires-Dist: pywin32; sys_platform == "win32"
Requires-Dist: pythonnet
Requires-Dist: h5py
Requires-Dist: numba
Requires-Dist: pandas
Requires-Dist: numpy
Requires-Dist: pyteomics
Requires-Dist: lxml
Requires-Dist: alphabase>=1.5.0
Requires-Dist: alphatims
Provides-Extra: stable
Requires-Dist: pywin32>=0.0.1; sys_platform == "win32" and extra == "stable"
Requires-Dist: pythonnet==3.0.3; extra == "stable"
Requires-Dist: h5py==3.11.0; extra == "stable"
Requires-Dist: numba==0.59.1; extra == "stable"
Requires-Dist: pandas==2.2.2; extra == "stable"
Requires-Dist: numpy==1.26.4; extra == "stable"
Requires-Dist: pyteomics==4.7.2; extra == "stable"
Requires-Dist: lxml==5.2.2; extra == "stable"
Requires-Dist: alphabase>=1.5.0; extra == "stable"
Requires-Dist: alphatims>=0.0.1; extra == "stable"
Provides-Extra: viz
Requires-Dist: plotly; extra == "viz"
Provides-Extra: tests
Requires-Dist: matplotlib; extra == "tests"
Requires-Dist: seaborn; extra == "tests"
Requires-Dist: pytest; extra == "tests"
Requires-Dist: nbmake==1.5.3; extra == "tests"
Requires-Dist: requests; extra == "tests"
Requires-Dist: plotly; extra == "tests"
Provides-Extra: docs
Requires-Dist: autodocsumm; extra == "docs"
Requires-Dist: myst_parser; extra == "docs"
Requires-Dist: sphinx; extra == "docs"
Requires-Dist: nbsphinx; extra == "docs"
Requires-Dist: jinja2; extra == "docs"
Requires-Dist: contextfilter; extra == "docs"
Requires-Dist: furo; extra == "docs"
Provides-Extra: development
Requires-Dist: jupyter; extra == "development"
Requires-Dist: bump-my-version; extra == "development"
Requires-Dist: ipykernel; extra == "development"
Requires-Dist: pre-commit==3.7.0; extra == "development"
Requires-Dist: matplotlib; extra == "development"
Requires-Dist: seaborn; extra == "development"
Requires-Dist: pytest; extra == "development"
Requires-Dist: nbmake==1.5.3; extra == "development"
Requires-Dist: requests; extra == "development"
Requires-Dist: autodocsumm; extra == "development"
Requires-Dist: myst_parser; extra == "development"
Requires-Dist: sphinx; extra == "development"
Requires-Dist: nbsphinx; extra == "development"
Requires-Dist: jinja2; extra == "development"
Requires-Dist: contextfilter; extra == "development"
Requires-Dist: furo; extra == "development"
Dynamic: license-file
